COPYRIGHT
MANIFEST.in
Makefile
README
setup.cfg
setup.py
test/__init__.py
test/__init__.pyc
test/test_compile.py
test/test_decorate.py
test/__pycache__/test_compile.cpython-27-PYTEST.pyc
test/__pycache__/test_decorate.cpython-27-PYTEST.pyc
tiddlywebplugins/__init__.py
tiddlywebplugins/utils.py
tiddlywebplugins.utils.egg-info/PKG-INFO
tiddlywebplugins.utils.egg-info/SOURCES.txt
tiddlywebplugins.utils.egg-info/dependency_links.txt
tiddlywebplugins.utils.egg-info/namespace_packages.txt
tiddlywebplugins.utils.egg-info/not-zip-safe
tiddlywebplugins.utils.egg-info/requires.txt
tiddlywebplugins.utils.egg-info/top_level.txt