Metadata-Version: 1.0
Name: tiddlywebplugins.utils
Version: 1.10
Summary: Tools and methods for managing TiddlyWeb plugins
Home-page: http://pypi.python.org/pypi/tiddlywebplugins.utils
Author: Chris Dent
Author-email: cdent@peermore.com
License: UNKNOWN
Platform: Posix; MacOS X; Windows
